{"main":{"css":"/css/main.781c6d99.css","js":"/main.5d8dcaf96665f2931d14.js"},"":{"ico":"/favicon.ico","js":["/163.b52229d18071e405f08d.js","/912.c93ccf0dc2d89c6c9b06.js","/307.a8e2d86a34eff91d4451.js","/258.50e32bf5bdd64be359dc.js","/887.b865158aa948545a12e9.js","/815.7526ffbf3d2b8030c787.js","/572.f9b4cdbb5f0eb3d7b629.js","/547.426f03a32f64babce654.js","/284.f384598c5020d709305a.js","/585.4e388456e7e27ae60dec.js","/264.3492b4e2d61b184bbdf2.js","/102.657101bf28769573d053.js","/875.3b2e3d65eeb02ec53a31.js","/sw.js","/917.6d59a09b3c5ec7ae9bb4.js","/733.dbc7749c8ec8add1235a.js","/739.538c4a2346e4e35f60a0.js","/927.c76172829da5136fa0cd.js","/624.5fbd86ec6f6669f9684b.js","/251.8edadaa51a8d09371661.js","/100.c266d12a4453d72ecbfa.js","/preInit/preload.js"],"css":["/css/887.b4dfdf20.css","/css/284.0851bf4c.css","/css/547.1c63e786.css","/css/264.21e03718.css","/css/815.f4d32b5b.css","/preInit/preload.css","/css/102.a52a870a.css","/css/875.55f0c043.css","/css/572.57d4b9c7.css","/css/585.57d4b9c7.css","/css/733.31647bb0.css","/css/739.8c5b220b.css"],"json":["/locales/ru/translation.json","/locales/ru/profile.json","/locales/en/translation.json","/locales/ru/article-detail.json","/locales/en/profile.json","/locales/ru/article.json","/locales/en/article-detail.json","/locales/en/article.json","/locales/ru/about.json","/locales/ru/not_found.json","/locales/ru/main.json","/locales/en/not_found.json","/locales/en/about.json","/locales/en/main.json"],"html":"/index.html","webmanifest":"/manifest.webmanifest"}}